AUTHORS
COPYING
MANIFEST.in
README.md
setup.py
django_extratest.egg-info/PKG-INFO
django_extratest.egg-info/SOURCES.txt
django_extratest.egg-info/dependency_links.txt
django_extratest.egg-info/requires.txt
django_extratest.egg-info/top_level.txt
extratest/__init__.py
extratest/app.py
extratest/base.py
testapp/__init__.py
testapp/manage.py
testapp/models.py
testapp/settings.py
testapp/test.py
testapp/urls.py
testapp/wsgi.py
testapp/migrations/0001_initial.py
testapp/migrations/__init__.py