Metadata-Version: 1.0
Name: django-extratest
Version: 1.6
Summary: Django extra useful test base classes
Home-page: https://gitlab.com/doctormo/django-extratest
Author: Martin Owens
Author-email: doctormo@gmail.com
License: LGPLv3
Platform: linux
